tvmodels/__init__.py
tvmodels/utils.py
tvmodels/version.py
tvmodels/models/__init__.py
tvmodels/models/efficientnet.py
tvmodels/models/layers.py
tvmodels/models/resnet.py
tvmodels/models/resnext.py
tvmodels/models/senet.py
tvmodels/models/blocks/__init__.py
tvmodels/models/blocks/effnet_blocks.py
tvmodels/models/blocks/res_blocks.py
tvmodels/models/blocks/se_blocks.py
tvmodels-0.0.7.dist-info/LICENSE
tvmodels-0.0.7.dist-info/METADATA
tvmodels-0.0.7.dist-info/WHEEL
tvmodels-0.0.7.dist-info/top_level.txt
tvmodels-0.0.7.dist-info/RECORD
