Metadata-Version: 2.1
Name: tvmodels
Version: 0.0.7
Summary: Implementation of vision models with their pretrained weights
Home-page: https://github.com/rohitgr7/tvmodels
Author: Rohit Gupta
Author-email: rohitgr1998@gmail.com
License: UNKNOWN
Platform: UNKNOWN
Classifier: Development Status :: 5 - Production/Stable
Classifier: Intended Audience :: Developers
Classifier: License :: OSI Approved :: MIT License
Classifier: Natural Language :: English
Classifier: Programming Language :: Python :: 3.6
Classifier: Programming Language :: Python :: 3.7
Classifier: Operating System :: OS Independent
Requires-Dist: torch (>=1.0.1)
Requires-Dist: numpy
Requires-Dist: requests
